src/insidesrc/__init__.py
src/insidesrc/example.py
Jenkins_Transfers_Testing-0.0.1.dist-info/LICENSE
Jenkins_Transfers_Testing-0.0.1.dist-info/METADATA
Jenkins_Transfers_Testing-0.0.1.dist-info/WHEEL
Jenkins_Transfers_Testing-0.0.1.dist-info/top_level.txt
Jenkins_Transfers_Testing-0.0.1.dist-info/RECORD
